setup.py
airohit_fasterrcnn.egg-info/PKG-INFO
airohit_fasterrcnn.egg-info/SOURCES.txt
airohit_fasterrcnn.egg-info/dependency_links.txt
airohit_fasterrcnn.egg-info/requires.txt
airohit_fasterrcnn.egg-info/top_level.txt
backbone_fasterrcnn/__init__.py
backbone_fasterrcnn/feature_pyramid_network.py
backbone_fasterrcnn/mobilenetv2_model.py
backbone_fasterrcnn/resnet50_fpn_model.py
backbone_fasterrcnn/vgg_model.py
network_files_fasterrcnn/__init__.py
network_files_fasterrcnn/boxes.py
network_files_fasterrcnn/det_utils.py
network_files_fasterrcnn/faster_rcnn_framework.py
network_files_fasterrcnn/image_list.py
network_files_fasterrcnn/roi_head.py
network_files_fasterrcnn/rpn_function.py
network_files_fasterrcnn/transform.py