Metadata-Version: 2.1
Name: airohit-fasterrcnn
Version: 1.0.0
Summary: a library for fasterrcnn detect
Author: airohit.com
